tenuki/__init__.py
tenuki/egf.py
tenuki/py.typed
tenuki/rank.py
tenuki-0.2.0.dist-info/METADATA
tenuki-0.2.0.dist-info/WHEEL
tenuki-0.2.0.dist-info/top_level.txt
tenuki-0.2.0.dist-info/RECORD
