Metadata-Version: 2.1
Name: tenuki
Version: 0.2.0
Summary: A set of development tools for go/baduk/wéiqí projects.
Home-page: https://github.com/konradhalas/tenuki
Author: Konrad Hałas
Author-email: halas.konrad@gmail.com
License: MIT
Classifier: Development Status :: 3 - Alpha
Classifier: Intended Audience :: Developers
Classifier: License :: OSI Approved :: MIT License
Classifier: Operating System :: OS Independent
Classifier: Programming Language :: Python
Classifier: Programming Language :: Python :: 3.11
Classifier: Topic :: Software Development :: Libraries :: Python Modules
Requires-Python: >=3.11
Provides-Extra: dev
Requires-Dist: pytest (>=7.4) ; extra == 'dev'
Requires-Dist: black ; extra == 'dev'
Requires-Dist: mypy ; extra == 'dev'
